pyfcrypt/__init__.py
pyfcrypt/fcrypt.py
pyfcrypt/rsa.py
pyfcrypt/rsa_gen.py
pyfcrypt-1.0.3.dist-info/LICENSE.txt
pyfcrypt-1.0.3.dist-info/METADATA
pyfcrypt-1.0.3.dist-info/WHEEL
pyfcrypt-1.0.3.dist-info/entry_points.txt
pyfcrypt-1.0.3.dist-info/top_level.txt
pyfcrypt-1.0.3.dist-info/RECORD
